rule_engine/__init__.py
rule_engine/action.py
rule_engine/condition.py
rule_engine/engine.py
rule_engine/main.py
rule_engine/rule.py
rule_engine/utils.py
ruleengine/__init__.py
ruleengine/engine.py
ruleengine/sample_runner.py
ruleengine/dsl/__init__.py
ruleengine/dsl/action.py
ruleengine/dsl/base_actions.py
ruleengine/dsl/base_conditions.py
ruleengine/dsl/condition.py
ruleengine/dsl/log_conditions.py
ruleengine/dsl/sequence_conditions.py
ruleengine/dsl/validation/__init__.py
ruleengine/dsl/validation/actions.py
ruleengine/dsl/validation/ast.py
ruleengine/dsl/validation/config_validator.py
ruleengine/dsl/validation/main.py
ruleengine/dsl/validation/normalizer.py
ruleengine/dsl/validation/validation_result.py
ruleengine/dsl/validation/validator.py
tests/__init__.py
tests/test_action.py
tests/test_condition.py
tests/test_engine.py
tests/test_rule.py
tests/dsl/__init__.py
tests/dsl/test_base_conditions.py
tests/dsl/test_condition.py
tests/dsl/test_log_conditions.py
tests/dsl/test_normalizer.py
tests/dsl/test_sequence_conditions.py
tests/dsl/utils.py
cos_ruleengine-0.1.39.dist-info/LICENSE
cos_ruleengine-0.1.39.dist-info/METADATA
cos_ruleengine-0.1.39.dist-info/WHEEL
cos_ruleengine-0.1.39.dist-info/top_level.txt
cos_ruleengine-0.1.39.dist-info/RECORD
