Metadata-Version: 2.1
Name: cos-ruleengine
Version: 0.1.39
Requires-Python: >=3.7
License-File: LICENSE
Requires-Dist: cel-python==0.1.5
Requires-Dist: pydantic==2.9.2
Requires-Dist: astor==0.8.1
Provides-Extra: dev
Requires-Dist: black~=24.3.0; extra == "dev"
Requires-Dist: flake8~=6.1.0; extra == "dev"
Requires-Dist: flake8-black~=0.3.3; extra == "dev"
Requires-Dist: pytest~=7.4.0; extra == "dev"
Requires-Dist: pytest-cov~=4.1.0; extra == "dev"
Requires-Dist: pytest-black~=0.3.12; extra == "dev"
